mysql_compare/__init__.py
mysql_compare/__main__.py
mysql_compare/_mysql_compare_table.py
mysql_compare/common.py
mysql_compare/forward.py
mysql_compare/forward12.py
mysql_compare/mysql_compare.py
mysql_compare/mysql_compare_forward.py
mysql_compare/mysql_compare_reverse.py
mysql_compare/nokey.py
mysql_compare/repair.py
mysql_compare-0.7.16.dist-info/METADATA
mysql_compare-0.7.16.dist-info/WHEEL
mysql_compare-0.7.16.dist-info/top_level.txt
mysql_compare-0.7.16.dist-info/RECORD
