Metadata-Version: 2.4
Name: mysql-compare
Version: 0.7.16
Requires-Python: >=3.10
Requires-Dist: mysql-connector-python==9.0.0
Dynamic: requires-dist
Dynamic: requires-python
